{
  "release_target": "v1.0.0",
  "ok": true,
  "checks": [
    {
      "name": "required-files",
      "ok": true,
      "detail": "all required release files exist"
    },
    {
      "name": "python-dependency-sources",
      "ok": true,
      "detail": "runtime and dev dependency sources match pyproject"
    },
    {
      "name": "python-locks",
      "ok": true,
      "detail": "python lockfiles contain pinned package entries"
    },
    {
      "name": "frontend-manifest",
      "ok": true,
      "detail": "frontend package manifest uses exact top-level versions matching package-lock"
    },
    {
      "name": "actions-pinning",
      "ok": true,
      "detail": "GitHub Actions are pinned to concrete commit SHAs"
    },
    {
      "name": "image-pinning",
      "ok": true,
      "detail": "release Dockerfiles and Compose files use explicit tags plus digests"
    },
    {
      "name": "tool-pinning",
      "ok": true,
      "detail": "global release tools are pinned and version-checked"
    },
    {
      "name": "ci-release-paths",
      "ok": true,
      "detail": "CI uses locked Python deps, npm ci, pinned Node, and release gate"
    },
    {
      "name": "apt-snapshots",
      "ok": true,
      "detail": "apt packages are installed through fixed Debian/Ubuntu snapshot configuration"
    },
    {
      "name": "client-surface-release-gate",
      "ok": true,
      "detail": "surface status overview: eclipse_plugin=runtime_mvp, eclipse_views_extension=runtime_mvp, nvim_plugin=runtime_mvp, tui_surface=runtime_mvp, vim_plugin=deferred, vscode_plugin=runtime_mvp"
    },
    {
      "name": "runtime-path-hygiene",
      "ok": true,
      "detail": "no forbidden runtime paths are tracked"
    },
    {
      "name": "dyndns-secret-hygiene",
      "ok": true,
      "detail": "DynDNS script/example enforce credential-safe behavior"
    },
    {
      "name": "compose-config",
      "ok": true,
      "detail": "release compose configurations render successfully"
    }
  ]
}
